[
  {
    "anchor": [
      "body",
      0,
      0,
      0,
      0
    ],
    "breadcrumb": "Document Root",
    "style": "Normal",
    "text": "rfp-asd-2349991-V3",
    "level": 0
  },
  {
    "anchor": [
      "body",
      0,
      0,
      0,
      1
    ],
    "breadcrumb": "Document Root",
    "style": "Normal",
    "text": "Generated: 2025-09-27 14:20:39",
    "level": 0
  },
  {
    "anchor": [
      "body",
      0,
      0,
      0,
      2
    ],
    "breadcrumb": "Document Root",
    "style": "Normal",
    "text": "Document Version: 1.0",
    "level": 0
  },
  {
    "anchor": [
      "body",
      0,
      0,
      0,
      3
    ],
    "breadcrumb": "Document Root",
    "style": "Normal",
    "text": "Total Sections: 10",
    "level": 0
  },
  {
    "anchor": [
      "body",
      0,
      0,
      0,
      5
    ],
    "breadcrumb": "Document Root",
    "style": "Normal",
    "text": "RFP-OLools-9903",
    "level": 0
  },
  {
    "anchor": [
      "body",
      0,
      0,
      0,
      6
    ],
    "breadcrumb": "1. Summary\nThis document is the application for CP",
    "style": "Heading 2",
    "text": "1. Summary\nThis document is the application for CPX's RFP, which presents the Cyber Security Management Project.",
    "level": 2
  },
  {
    "anchor": [
      "body",
      0,
      0,
      0,
      7
    ],
    "breadcrumb": "Document Root",
    "style": "Normal",
    "text": "--\t• Executive Overview - Tony Stark",
    "level": 0
  },
  {
    "anchor": [
      "body",
      0,
      0,
      0,
      8
    ],
    "breadcrumb": "Document Root",
    "style": "Normal",
    "text": "--\t   • Key Benefits",
    "level": 0
  },
  {
    "anchor": [
      "body",
      0,
      0,
      0,
      9
    ],
    "breadcrumb": "Document Root",
    "style": "Normal",
    "text": "--\t   • Competitive Advantages",
    "level": 0
  },
  {
    "anchor": [
      "body",
      0,
      0,
      0,
      10
    ],
    "breadcrumb": "Document Root",
    "style": "Normal",
    "text": "--\t   • Success Metrics",
    "level": 0
  },
  {
    "anchor": [
      "body",
      0,
      0,
      0,
      12
    ],
    "breadcrumb": "2. About CPX",
    "style": "Heading 2",
    "text": "2. About CPX",
    "level": 2
  },
  {
    "anchor": [
      "body",
      0,
      0,
      0,
      13
    ],
    "breadcrumb": "Document Root",
    "style": "Normal",
    "text": "--\t   • 2.1. CPX Purpose & Value",
    "level": 0
  },
  {
    "anchor": [
      "body",
      0,
      0,
      0,
      14
    ],
    "breadcrumb": "Document Root",
    "style": "Normal",
    "text": "--\t   • 2.2. Key Information",
    "level": 0
  },
  {
    "anchor": [
      "body",
      0,
      0,
      0,
      15
    ],
    "breadcrumb": "Document Root",
    "style": "Normal",
    "text": "--\t   • 2.3. Certifications & Accreditations",
    "level": 0
  },
  {
    "anchor": [
      "body",
      0,
      0,
      0,
      16
    ],
    "breadcrumb": "Document Root",
    "style": "Normal",
    "text": "--\t   • 2.4. Organizational Structure",
    "level": 0
  },
  {
    "anchor": [
      "body",
      0,
      0,
      0,
      17
    ],
    "breadcrumb": "Document Root",
    "style": "Normal",
    "text": "--\t   • 2.5. Team Composition",
    "level": 0
  },
  {
    "anchor": [
      "body",
      0,
      0,
      0,
      19
    ],
    "breadcrumb": "3. Understanding of Requirements",
    "style": "Heading 2",
    "text": "3. Understanding of Requirements",
    "level": 2
  },
  {
    "anchor": [
      "body",
      0,
      0,
      0,
      20
    ],
    "breadcrumb": "Document Root",
    "style": "Normal",
    "text": "----media/image2.png----",
    "level": 0
  },
  {
    "anchor": [
      "body",
      0,
      0,
      0,
      21
    ],
    "breadcrumb": "Document Root",
    "style": "Normal",
    "text": "----media/image2.png----",
    "level": 0
  },
  {
    "anchor": [
      "body",
      0,
      0,
      0,
      23
    ],
    "breadcrumb": "Document Root",
    "style": "Normal",
    "text": "--\t   • 3.1. Project Scope Analysis",
    "level": 0
  },
  {
    "anchor": [
      "body",
      0,
      0,
      0,
      24
    ],
    "breadcrumb": "Document Root",
    "style": "Normal",
    "text": "--\t   • 3.2. Stakeholder Requirements",
    "level": 0
  },
  {
    "anchor": [
      "body",
      0,
      0,
      0,
      25
    ],
    "breadcrumb": "Document Root",
    "style": "Normal",
    "text": "--\t   • 3.3. Success Criteria",
    "level": 0
  },
  {
    "anchor": [
      "body",
      0,
      0,
      0,
      26
    ],
    "breadcrumb": "Document Root",
    "style": "Normal",
    "text": "--\t   • 3.4. Risk Assessment",
    "level": 0
  },
  {
    "anchor": [
      "body",
      0,
      0,
      0,
      28
    ],
    "breadcrumb": "4. Proposed Solution",
    "style": "Heading 2",
    "text": "4. Proposed Solution",
    "level": 2
  },
  {
    "anchor": [
      "body",
      0,
      0,
      0,
      29
    ],
    "breadcrumb": "Document Root",
    "style": "Normal",
    "text": "----media/image1.png----",
    "level": 0
  },
  {
    "anchor": [
      "body",
      0,
      0,
      0,
      30
    ],
    "breadcrumb": "Document Root",
    "style": "Normal",
    "text": "----media/image1.png----",
    "level": 0
  },
  {
    "anchor": [
      "body",
      0,
      0,
      0,
      31
    ],
    "breadcrumb": "Document Root",
    "style": "Normal",
    "text": "----media/image2.png----",
    "level": 0
  },
  {
    "anchor": [
      "body",
      0,
      0,
      0,
      32
    ],
    "breadcrumb": "Document Root",
    "style": "Normal",
    "text": "----media/image1.png----",
    "level": 0
  },
  {
    "anchor": [
      "body",
      0,
      0,
      0,
      33
    ],
    "breadcrumb": "Document Root",
    "style": "Normal",
    "text": "----media/image2.png----",
    "level": 0
  },
  {
    "anchor": [
      "body",
      0,
      0,
      0,
      34
    ],
    "breadcrumb": "Document Root",
    "style": "Normal",
    "text": "----media/image1.png----",
    "level": 0
  },
  {
    "anchor": [
      "body",
      0,
      0,
      0,
      36
    ],
    "breadcrumb": "Document Root",
    "style": "Normal",
    "text": "--\t   • 4.1. Technical Architecture",
    "level": 0
  },
  {
    "anchor": [
      "body",
      0,
      0,
      0,
      37
    ],
    "breadcrumb": "Document Root",
    "style": "Normal",
    "text": "--\t   • 4.2. Implementation Approach",
    "level": 0
  },
  {
    "anchor": [
      "body",
      0,
      0,
      0,
      38
    ],
    "breadcrumb": "Document Root",
    "style": "Normal",
    "text": "--\t   • 4.3. Solution Components",
    "level": 0
  },
  {
    "anchor": [
      "body",
      0,
      0,
      0,
      39
    ],
    "breadcrumb": "Document Root",
    "style": "Normal",
    "text": "--\t   • 4.4. Integration Strategy",
    "level": 0
  },
  {
    "anchor": [
      "body",
      0,
      0,
      0,
      41
    ],
    "breadcrumb": "5. Implementation Plan",
    "style": "Heading 2",
    "text": "5. Implementation Plan",
    "level": 2
  },
  {
    "anchor": [
      "body",
      0,
      0,
      0,
      42
    ],
    "breadcrumb": "Document Root",
    "style": "Normal",
    "text": "----media/image4.png----",
    "level": 0
  },
  {
    "anchor": [
      "body",
      0,
      0,
      0,
      43
    ],
    "breadcrumb": "Document Root",
    "style": "Normal",
    "text": "----media/image3.png----",
    "level": 0
  },
  {
    "anchor": [
      "body",
      0,
      0,
      0,
      44
    ],
    "breadcrumb": "Document Root",
    "style": "Normal",
    "text": "--\t   • 5.1. Project Phases",
    "level": 0
  },
  {
    "anchor": [
      "body",
      0,
      0,
      0,
      45
    ],
    "breadcrumb": "Document Root",
    "style": "Normal",
    "text": "--\t   • 5.2. Timeline & Milestones",
    "level": 0
  },
  {
    "anchor": [
      "body",
      0,
      0,
      0,
      46
    ],
    "breadcrumb": "Document Root",
    "style": "Normal",
    "text": "--\t   • 5.3. Resource Allocation",
    "level": 0
  },
  {
    "anchor": [
      "body",
      0,
      0,
      0,
      47
    ],
    "breadcrumb": "Document Root",
    "style": "Normal",
    "text": "--\t   • 5.4. Quality Assurance",
    "level": 0
  },
  {
    "anchor": [
      "body",
      0,
      0,
      0,
      49
    ],
    "breadcrumb": "6. Team and Experience",
    "style": "Heading 2",
    "text": "6. Team and Experience",
    "level": 2
  },
  {
    "anchor": [
      "body",
      0,
      0,
      0,
      51
    ],
    "breadcrumb": "Document Root",
    "style": "Normal",
    "text": "--\t   • 6.1. Core Team Members",
    "level": 0
  },
  {
    "anchor": [
      "body",
      0,
      0,
      0,
      52
    ],
    "breadcrumb": "Document Root",
    "style": "Normal",
    "text": "--\t   • 6.2. Relevant Experience",
    "level": 0
  },
  {
    "anchor": [
      "body",
      0,
      0,
      0,
      53
    ],
    "breadcrumb": "Document Root",
    "style": "Normal",
    "text": "--\t   • 6.3. Similar Projects",
    "level": 0
  },
  {
    "anchor": [
      "body",
      0,
      0,
      0,
      54
    ],
    "breadcrumb": "Document Root",
    "style": "Normal",
    "text": "--\t   • 6.4. Client References",
    "level": 0
  },
  {
    "anchor": [
      "body",
      0,
      0,
      0,
      56
    ],
    "breadcrumb": "Document Root",
    "style": "Normal",
    "text": "Updated RFP Response",
    "level": 0
  },
  {
    "anchor": [
      "body",
      0,
      0,
      0,
      57
    ],
    "breadcrumb": "Document Root",
    "style": "Normal",
    "text": "--\t   • 7.1. Cost Breakdown",
    "level": 0
  },
  {
    "anchor": [
      "body",
      0,
      0,
      0,
      58
    ],
    "breadcrumb": "Document Root",
    "style": "Normal",
    "text": "--\t   • 7.2. Pricing Model",
    "level": 0
  },
  {
    "anchor": [
      "body",
      0,
      0,
      0,
      59
    ],
    "breadcrumb": "Document Root",
    "style": "Normal",
    "text": "--\t   • 7.3. Payment Terms",
    "level": 0
  },
  {
    "anchor": [
      "body",
      0,
      0,
      0,
      60
    ],
    "breadcrumb": "Document Root",
    "style": "Normal",
    "text": "--\t   • 7.4. Value Analysis",
    "level": 0
  },
  {
    "anchor": [
      "body",
      0,
      0,
      0,
      62
    ],
    "breadcrumb": "Document Root",
    "style": "Normal",
    "text": "## Finance Team Response\n\n### Budget Overview\n- Total project budget: $2,000,000 - $5,000,000\n- Ongoing operational costs: $200,000 - $500,000 annually\n- Cost optimization and savings targets\n- ROI analysis and justification\n\n### Budget Breakdown\n| Item                        | Cost Estimate    |\n|-----------------------------|------------------|\n| Software Development        | $1,500,000       |\n| Hardware Infrastructure     | $500,000         |\n| Training and Implementation | $300,000         |\n| Contingency                 | $200,000         |\n| Total                       | $2,500,000       |\n\n### Pricing Model and Payment Terms\n- Fixed-price contract with milestone payments\n- 30% upfront, 30% at project midpoint, 40% upon completion\n- Payment terms: Net 30 days\n\n### Financial Justifications and ROI Analysis\n- Cost savings from process automation and error reduction\n- Improved data visibility leading to better decision-making\n- Enhanced user experience and productivity gains\n- Scalability and maintainability benefits\n- ROI projected at 20% over 3 years\n\n### Cost-Benefit Analysis\n- Cost savings vs. operational efficiency improvements\n- Long-term benefits vs. initial investment\n- Value proposition compared to alternative solutions\n\n### Resource Allocation\n- Dedicated project team with relevant expertise\n- Allocation of resources based on project phases and requirements\n- Backup resources identified for risk mitigation\n\n### Financial Risk Assessment\n- Identified technical risks and mitigation strategies\n- Contingency planning for schedule risks\n- Resource risks addressed with backup plans\n- Quality risks mitigated through testing procedures\n\n### Payment Schedules and Milestones\n- Milestone 1: Software Development Kickoff - 30% payment\n- Milestone 2: System Testing and User Training - 30% payment\n- Milestone 3: Go-Live and Implementation - 40% payment\n\nEnsure all financial content is accurate, compliant with industry standards, transparent, detailed, and aligned with the client's requirements.",
    "level": 0
  },
  {
    "anchor": [
      "body",
      0,
      0,
      0,
      63
    ],
    "breadcrumb": "Document Root",
    "style": "Normal",
    "text": "--\t   • 8.1. Contractual Terms",
    "level": 0
  },
  {
    "anchor": [
      "body",
      0,
      0,
      0,
      64
    ],
    "breadcrumb": "Document Root",
    "style": "Normal",
    "text": "--\t   • 8.2. Service Level Agreements",
    "level": 0
  },
  {
    "anchor": [
      "body",
      0,
      0,
      0,
      65
    ],
    "breadcrumb": "Document Root",
    "style": "Normal",
    "text": "--\t   • 8.3. Liability & Warranty",
    "level": 0
  },
  {
    "anchor": [
      "body",
      0,
      0,
      0,
      66
    ],
    "breadcrumb": "Document Root",
    "style": "Normal",
    "text": "--\t   • 8.4. Intellectual Property",
    "level": 0
  },
  {
    "anchor": [
      "body",
      0,
      0,
      0,
      68
    ],
    "breadcrumb": "9. Additional Services",
    "style": "Heading 2",
    "text": "9. Additional Services",
    "level": 2
  },
  {
    "anchor": [
      "body",
      0,
      0,
      0,
      70
    ],
    "breadcrumb": "Document Root",
    "style": "Normal",
    "text": "--\t   • 9.1. Optional Modules",
    "level": 0
  },
  {
    "anchor": [
      "body",
      0,
      0,
      0,
      71
    ],
    "breadcrumb": "Document Root",
    "style": "Normal",
    "text": "--\t   • 9.2. Future Enhancements",
    "level": 0
  },
  {
    "anchor": [
      "body",
      0,
      0,
      0,
      72
    ],
    "breadcrumb": "Document Root",
    "style": "Normal",
    "text": "--\t   • 9.3. Support Services",
    "level": 0
  },
  {
    "anchor": [
      "body",
      0,
      0,
      0,
      73
    ],
    "breadcrumb": "Document Root",
    "style": "Normal",
    "text": "--\t   • 9.4. Training Programs",
    "level": 0
  },
  {
    "anchor": [
      "body",
      0,
      0,
      0,
      75
    ],
    "breadcrumb": "10. Appendices",
    "style": "Heading 2",
    "text": "10. Appendices",
    "level": 2
  },
  {
    "anchor": [
      "body",
      0,
      0,
      0,
      76
    ],
    "breadcrumb": "Document Root",
    "style": "Normal",
    "text": "--\t   • 10.1. Technical Specifications",
    "level": 0
  },
  {
    "anchor": [
      "body",
      0,
      0,
      0,
      77
    ],
    "breadcrumb": "Document Root",
    "style": "Normal",
    "text": "--\t   • 10.2. Certifications",
    "level": 0
  },
  {
    "anchor": [
      "body",
      0,
      0,
      0,
      78
    ],
    "breadcrumb": "Document Root",
    "style": "Normal",
    "text": "--\t   • 10.3. Case Studies",
    "level": 0
  },
  {
    "anchor": [
      "body",
      0,
      0,
      0,
      79
    ],
    "breadcrumb": "Document Root",
    "style": "Normal",
    "text": "--\t   • 10.4. Additional Documentation",
    "level": 0
  },
  {
    "anchor": [
      "body",
      0,
      0,
      0,
      82
    ],
    "breadcrumb": "1. Summary",
    "style": "Heading 2",
    "text": "1. Summary",
    "level": 2
  },
  {
    "anchor": [
      "body",
      0,
      0,
      0,
      83
    ],
    "breadcrumb": "Document Root",
    "style": "Normal",
    "text": "Section Structure:",
    "level": 0
  },
  {
    "anchor": [
      "body",
      0,
      0,
      0,
      84
    ],
    "breadcrumb": "Document Root",
    "style": "Normal",
    "text": "--\t• Executive Overview",
    "level": 0
  },
  {
    "anchor": [
      "body",
      0,
      0,
      0,
      85
    ],
    "breadcrumb": "Document Root",
    "style": "Normal",
    "text": "--\t• Key Benefits",
    "level": 0
  },
  {
    "anchor": [
      "body",
      0,
      0,
      0,
      86
    ],
    "breadcrumb": "Document Root",
    "style": "Normal",
    "text": "--\t• Competitive Advantages",
    "level": 0
  },
  {
    "anchor": [
      "body",
      0,
      0,
      0,
      87
    ],
    "breadcrumb": "Document Root",
    "style": "Normal",
    "text": "--\t• Success Metrics",
    "level": 0
  },
  {
    "anchor": [
      "body",
      0,
      0,
      0,
      89
    ],
    "breadcrumb": "Document Root",
    "style": "Normal",
    "text": "Executive Overview",
    "level": 0
  },
  {
    "anchor": [
      "body",
      0,
      0,
      0,
      90
    ],
    "breadcrumb": "Document Root",
    "style": "Normal",
    "text": "This proposal, led by CEO Yashaswa Varshney, presents a comprehensive solution designed to meet your organization's specific requirements. Our multi-disciplinary team has analyzed the requirements and developed an integrated approach that leverages cutting-edge technology, proven methodologies, and industry best practices.",
    "level": 0
  },
  {
    "anchor": [
      "body",
      0,
      0,
      0,
      91
    ],
    "breadcrumb": "Document Root",
    "style": "Normal",
    "text": "Key Benefits",
    "level": 0
  },
  {
    "anchor": [
      "body",
      0,
      0,
      0,
      92
    ],
    "breadcrumb": "Document Root",
    "style": "Normal",
    "text": "- **Technical Excellence**: Robust, scalable architecture designed for long-term success",
    "level": 0
  },
  {
    "anchor": [
      "body",
      0,
      0,
      0,
      93
    ],
    "breadcrumb": "Document Root",
    "style": "Normal",
    "text": "- **Financial Value**: Competitive pricing with clear ROI and value proposition",
    "level": 0
  },
  {
    "anchor": [
      "body",
      0,
      0,
      0,
      94
    ],
    "breadcrumb": "Document Root",
    "style": "Normal",
    "text": "- **Legal Compliance**: Full adherence to regulatory requirements and industry standards",
    "level": 0
  },
  {
    "anchor": [
      "body",
      0,
      0,
      0,
      95
    ],
    "breadcrumb": "Document Root",
    "style": "Normal",
    "text": "- **Quality Assurance**: Comprehensive testing and risk management processes",
    "level": 0
  },
  {
    "anchor": [
      "body",
      0,
      0,
      0,
      96
    ],
    "breadcrumb": "Document Root",
    "style": "Normal",
    "text": "Competitive Advantages",
    "level": 0
  },
  {
    "anchor": [
      "body",
      0,
      0,
      0,
      97
    ],
    "breadcrumb": "Document Root",
    "style": "Normal",
    "text": "- Multi-disciplinary team approach ensuring holistic solution design",
    "level": 0
  },
  {
    "anchor": [
      "body",
      0,
      0,
      0,
      98
    ],
    "breadcrumb": "Document Root",
    "style": "Normal",
    "text": "- Proven track record in similar projects and industries",
    "level": 0
  },
  {
    "anchor": [
      "body",
      0,
      0,
      0,
      99
    ],
    "breadcrumb": "Document Root",
    "style": "Normal",
    "text": "- Flexible implementation methodology adaptable to changing requirements",
    "level": 0
  },
  {
    "anchor": [
      "body",
      0,
      0,
      0,
      100
    ],
    "breadcrumb": "Document Root",
    "style": "Normal",
    "text": "- Comprehensive support and maintenance services",
    "level": 0
  },
  {
    "anchor": [
      "body",
      0,
      0,
      0,
      101
    ],
    "breadcrumb": "Document Root",
    "style": "Normal",
    "text": "Success Metrics",
    "level": 0
  },
  {
    "anchor": [
      "body",
      0,
      0,
      0,
      102
    ],
    "breadcrumb": "Document Root",
    "style": "Normal",
    "text": "- On-time delivery with milestone-based progress tracking",
    "level": 0
  },
  {
    "anchor": [
      "body",
      0,
      0,
      0,
      103
    ],
    "breadcrumb": "Document Root",
    "style": "Normal",
    "text": "- Budget adherence with transparent cost management",
    "level": 0
  },
  {
    "anchor": [
      "body",
      0,
      0,
      0,
      104
    ],
    "breadcrumb": "Document Root",
    "style": "Normal",
    "text": "- Quality standards exceeding industry benchmarks",
    "level": 0
  },
  {
    "anchor": [
      "body",
      0,
      0,
      0,
      105
    ],
    "breadcrumb": "Document Root",
    "style": "Normal",
    "text": "- Client satisfaction and long-term partnership development",
    "level": 0
  },
  {
    "anchor": [
      "body",
      0,
      0,
      0,
      107
    ],
    "breadcrumb": "2. About CPX",
    "style": "Heading 2",
    "text": "2. About CPX",
    "level": 2
  },
  {
    "anchor": [
      "body",
      0,
      0,
      0,
      108
    ],
    "breadcrumb": "Document Root",
    "style": "Normal",
    "text": "Section Structure:",
    "level": 0
  },
  {
    "anchor": [
      "body",
      0,
      0,
      0,
      109
    ],
    "breadcrumb": "Document Root",
    "style": "Normal",
    "text": "--\t• 2.1. CPX Purpose & Value",
    "level": 0
  },
  {
    "anchor": [
      "body",
      0,
      0,
      0,
      110
    ],
    "breadcrumb": "Document Root",
    "style": "Normal",
    "text": "--\t• 2.2. Key Information",
    "level": 0
  },
  {
    "anchor": [
      "body",
      0,
      0,
      0,
      111
    ],
    "breadcrumb": "Document Root",
    "style": "Normal",
    "text": "--\t• 2.3. Certifications & Accreditations",
    "level": 0
  },
  {
    "anchor": [
      "body",
      0,
      0,
      0,
      112
    ],
    "breadcrumb": "Document Root",
    "style": "Normal",
    "text": "--\t• 2.4. Organizational Structure",
    "level": 0
  },
  {
    "anchor": [
      "body",
      0,
      0,
      0,
      113
    ],
    "breadcrumb": "Document Root",
    "style": "Normal",
    "text": "--\t• 2.5. Team Composition",
    "level": 0
  },
  {
    "anchor": [
      "body",
      0,
      0,
      0,
      115
    ],
    "breadcrumb": "Document Root",
    "style": "Normal",
    "text": "Test Update",
    "level": 0
  },
  {
    "anchor": [
      "body",
      0,
      0,
      0,
      116
    ],
    "breadcrumb": "Document Root",
    "style": "Normal",
    "text": "CPX is a leading technology solutions provider specializing in enterprise-grade systems integration, custom software development, and digital transformation initiatives. Our purpose is to deliver innovative solutions that drive business growth and operational excellence.",
    "level": 0
  },
  {
    "anchor": [
      "body",
      0,
      0,
      0,
      117
    ],
    "breadcrumb": "2.2. Key Information",
    "style": "Heading 3",
    "text": "2.2. Key Information",
    "level": 3
  },
  {
    "anchor": [
      "body",
      0,
      0,
      0,
      118
    ],
    "breadcrumb": "Document Root",
    "style": "Normal",
    "text": "- **Founded**: 2015",
    "level": 0
  },
  {
    "anchor": [
      "body",
      0,
      0,
      0,
      119
    ],
    "breadcrumb": "Document Root",
    "style": "Normal",
    "text": "- **Headquarters**: Global presence with offices in major business centers",
    "level": 0
  },
  {
    "anchor": [
      "body",
      0,
      0,
      0,
      120
    ],
    "breadcrumb": "Document Root",
    "style": "Normal",
    "text": "- **Team Size**: 500+ certified professionals",
    "level": 0
  },
  {
    "anchor": [
      "body",
      0,
      0,
      0,
      121
    ],
    "breadcrumb": "Document Root",
    "style": "Normal",
    "text": "- **Industries Served**: Financial Services, Healthcare, Government, Manufacturing",
    "level": 0
  },
  {
    "anchor": [
      "body",
      0,
      0,
      0,
      122
    ],
    "breadcrumb": "Document Root",
    "style": "Normal",
    "text": "- **Client Base**: 200+ satisfied clients worldwide",
    "level": 0
  },
  {
    "anchor": [
      "body",
      0,
      0,
      0,
      123
    ],
    "breadcrumb": "2.3. Certifications & Accreditations",
    "style": "Heading 3",
    "text": "2.3. Certifications & Accreditations",
    "level": 3
  },
  {
    "anchor": [
      "body",
      0,
      0,
      0,
      124
    ],
    "breadcrumb": "Document Root",
    "style": "Normal",
    "text": "- ISO 27001 Information Security Management",
    "level": 0
  },
  {
    "anchor": [
      "body",
      0,
      0,
      0,
      125
    ],
    "breadcrumb": "Document Root",
    "style": "Normal",
    "text": "- ISO 9001 Quality Management Systems",
    "level": 0
  },
  {
    "anchor": [
      "body",
      0,
      0,
      0,
      126
    ],
    "breadcrumb": "Document Root",
    "style": "Normal",
    "text": "- CMMI Level 5 for Development and Services",
    "level": 0
  },
  {
    "anchor": [
      "body",
      0,
      0,
      0,
      127
    ],
    "breadcrumb": "Document Root",
    "style": "Normal",
    "text": "- Cloud platform certifications (AWS, Azure, GCP)",
    "level": 0
  },
  {
    "anchor": [
      "body",
      0,
      0,
      0,
      128
    ],
    "breadcrumb": "Document Root",
    "style": "Normal",
    "text": "- Industry-specific compliance certifications",
    "level": 0
  },
  {
    "anchor": [
      "body",
      0,
      0,
      0,
      129
    ],
    "breadcrumb": "2.4. Organizational Structure",
    "style": "Heading 3",
    "text": "2.4. Organizational Structure",
    "level": 3
  },
  {
    "anchor": [
      "body",
      0,
      0,
      0,
      131
    ],
    "breadcrumb": "Document Root",
    "style": "Normal",
    "text": "Our organization is structured around centers of excellence, ensuring deep domain expertise while maintaining agility and cross-functional collaboration.",
    "level": 0
  },
  {
    "anchor": [
      "body",
      0,
      0,
      0,
      132
    ],
    "breadcrumb": "2.5. Team Composition",
    "style": "Heading 3",
    "text": "2.5. Team Composition",
    "level": 3
  },
  {
    "anchor": [
      "body",
      0,
      0,
      0,
      134
    ],
    "breadcrumb": "Document Root",
    "style": "Normal",
    "text": "- **Technical Leadership**: Senior architects and technology leads",
    "level": 0
  },
  {
    "anchor": [
      "body",
      0,
      0,
      0,
      135
    ],
    "breadcrumb": "Document Root",
    "style": "Normal",
    "text": "- **Project Management**: Certified PMP and Agile practitioners",
    "level": 0
  },
  {
    "anchor": [
      "body",
      0,
      0,
      0,
      136
    ],
    "breadcrumb": "Document Root",
    "style": "Normal",
    "text": "- **Quality Assurance**: Dedicated QA and testing specialists",
    "level": 0
  },
  {
    "anchor": [
      "body",
      0,
      0,
      0,
      137
    ],
    "breadcrumb": "Document Root",
    "style": "Normal",
    "text": "- **Legal & Compliance**: In-house legal and compliance experts",
    "level": 0
  },
  {
    "anchor": [
      "body",
      0,
      0,
      0,
      139
    ],
    "breadcrumb": "3. Understanding of Requirements",
    "style": "Heading 2",
    "text": "3. Understanding of Requirements",
    "level": 2
  },
  {
    "anchor": [
      "body",
      0,
      0,
      0,
      140
    ],
    "breadcrumb": "Document Root",
    "style": "Normal",
    "text": "Section Structure:",
    "level": 0
  },
  {
    "anchor": [
      "body",
      0,
      0,
      0,
      141
    ],
    "breadcrumb": "Document Root",
    "style": "Normal",
    "text": "--\t• 3.1. Project Scope Analysis",
    "level": 0
  },
  {
    "anchor": [
      "body",
      0,
      0,
      0,
      142
    ],
    "breadcrumb": "Document Root",
    "style": "Normal",
    "text": "--\t• 3.2. Stakeholder Requirements",
    "level": 0
  },
  {
    "anchor": [
      "body",
      0,
      0,
      0,
      143
    ],
    "breadcrumb": "Document Root",
    "style": "Normal",
    "text": "--\t• 3.3. Success Criteria",
    "level": 0
  },
  {
    "anchor": [
      "body",
      0,
      0,
      0,
      144
    ],
    "breadcrumb": "Document Root",
    "style": "Normal",
    "text": "--\t• 3.4. Risk Assessment",
    "level": 0
  },
  {
    "anchor": [
      "body",
      0,
      0,
      0,
      146
    ],
    "breadcrumb": "3.1. Project Scope Analysis",
    "style": "Heading 3",
    "text": "3.1. Project Scope Analysis",
    "level": 3
  },
  {
    "anchor": [
      "body",
      0,
      0,
      0,
      147
    ],
    "breadcrumb": "Document Root",
    "style": "Normal",
    "text": "Based on our comprehensive analysis of the RFP requirements, we have identified the key scope elements and deliverables. Our understanding encompasses both functional and non-functional requirements, ensuring complete coverage of your needs.",
    "level": 0
  },
  {
    "anchor": [
      "body",
      0,
      0,
      0,
      148
    ],
    "breadcrumb": "3.2. Stakeholder Requirements",
    "style": "Heading 3",
    "text": "3.2. Stakeholder Requirements",
    "level": 3
  },
  {
    "anchor": [
      "body",
      0,
      0,
      0,
      149
    ],
    "breadcrumb": "Document Root",
    "style": "Normal",
    "text": "We have identified and analyzed requirements from all stakeholder groups, including end-users, technical teams, management, and compliance officers. Our solution addresses the unique needs of each stakeholder group.",
    "level": 0
  },
  {
    "anchor": [
      "body",
      0,
      0,
      0,
      150
    ],
    "breadcrumb": "3.3. Success Criteria",
    "style": "Heading 3",
    "text": "3.3. Success Criteria",
    "level": 3
  },
  {
    "anchor": [
      "body",
      0,
      0,
      0,
      151
    ],
    "breadcrumb": "Document Root",
    "style": "Normal",
    "text": "Clear, measurable success criteria have been established, including performance metrics, quality standards, timeline adherence, and user satisfaction benchmarks.",
    "level": 0
  },
  {
    "anchor": [
      "body",
      0,
      0,
      0,
      152
    ],
    "breadcrumb": "3.4. Risk Assessment",
    "style": "Heading 3",
    "text": "3.4. Risk Assessment",
    "level": 3
  },
  {
    "anchor": [
      "body",
      0,
      0,
      0,
      153
    ],
    "breadcrumb": "Document Root",
    "style": "Normal",
    "text": "Comprehensive risk analysis has been conducted, identifying potential challenges and developing mitigation strategies to ensure project success.",
    "level": 0
  },
  {
    "anchor": [
      "body",
      0,
      0,
      0,
      155
    ],
    "breadcrumb": "4. Proposed Solution",
    "style": "Heading 2",
    "text": "4. Proposed Solution",
    "level": 2
  },
  {
    "anchor": [
      "body",
      0,
      0,
      0,
      156
    ],
    "breadcrumb": "Document Root",
    "style": "Normal",
    "text": "Section Structure:",
    "level": 0
  },
  {
    "anchor": [
      "body",
      0,
      0,
      0,
      157
    ],
    "breadcrumb": "Document Root",
    "style": "Normal",
    "text": "--\t• 4.1. Technical Architecture",
    "level": 0
  },
  {
    "anchor": [
      "body",
      0,
      0,
      0,
      158
    ],
    "breadcrumb": "Document Root",
    "style": "Normal",
    "text": "--\t• 4.2. Implementation Approach",
    "level": 0
  },
  {
    "anchor": [
      "body",
      0,
      0,
      0,
      159
    ],
    "breadcrumb": "Document Root",
    "style": "Normal",
    "text": "--\t• 4.3. Solution Components",
    "level": 0
  },
  {
    "anchor": [
      "body",
      0,
      0,
      0,
      160
    ],
    "breadcrumb": "Document Root",
    "style": "Normal",
    "text": "--\t• 4.4. Integration Strategy",
    "level": 0
  },
  {
    "anchor": [
      "body",
      0,
      0,
      0,
      162
    ],
    "breadcrumb": "Document Root",
    "style": "Normal",
    "text": "Technical Architecture",
    "level": 0
  },
  {
    "anchor": [
      "body",
      0,
      0,
      0,
      163
    ],
    "breadcrumb": "Document Root",
    "style": "Normal",
    "text": "We propose a cloud-native, microservices architecture built on modern containerization platforms with automated CI/CD pipelines.",
    "level": 0
  },
  {
    "anchor": [
      "body",
      0,
      0,
      0,
      164
    ],
    "breadcrumb": "Document Root",
    "style": "Normal",
    "text": "----media/image5.png----",
    "level": 0
  },
  {
    "anchor": [
      "body",
      0,
      0,
      0,
      165
    ],
    "breadcrumb": "Document Root",
    "style": "Normal",
    "text": "----media/image5.png----",
    "level": 0
  },
  {
    "anchor": [
      "body",
      0,
      0,
      0,
      166
    ],
    "breadcrumb": "Document Root",
    "style": "Normal",
    "text": "----media/image5.png----",
    "level": 0
  },
  {
    "anchor": [
      "body",
      0,
      0,
      0,
      169
    ],
    "breadcrumb": "5. Implementation Plan",
    "style": "Heading 2",
    "text": "5. Implementation Plan",
    "level": 2
  },
  {
    "anchor": [
      "body",
      0,
      0,
      0,
      170
    ],
    "breadcrumb": "Document Root",
    "style": "Normal",
    "text": "Section Structure:",
    "level": 0
  },
  {
    "anchor": [
      "body",
      0,
      0,
      0,
      171
    ],
    "breadcrumb": "Document Root",
    "style": "Normal",
    "text": "--\t• 5.1. Project Phases",
    "level": 0
  },
  {
    "anchor": [
      "body",
      0,
      0,
      0,
      172
    ],
    "breadcrumb": "Document Root",
    "style": "Normal",
    "text": "--\t• 5.2. Timeline & Milestones",
    "level": 0
  },
  {
    "anchor": [
      "body",
      0,
      0,
      0,
      173
    ],
    "breadcrumb": "Document Root",
    "style": "Normal",
    "text": "--\t• 5.3. Resource Allocation",
    "level": 0
  },
  {
    "anchor": [
      "body",
      0,
      0,
      0,
      174
    ],
    "breadcrumb": "Document Root",
    "style": "Normal",
    "text": "--\t• 5.4. Quality Assurance",
    "level": 0
  },
  {
    "anchor": [
      "body",
      0,
      0,
      0,
      176
    ],
    "breadcrumb": "Document Root",
    "style": "Normal",
    "text": "Technical Architecture",
    "level": 0
  },
  {
    "anchor": [
      "body",
      0,
      0,
      0,
      177
    ],
    "breadcrumb": "Document Root",
    "style": "Normal",
    "text": "We propose a cloud-native, microservices architecture built on modern containerization platforms with automated CI/CD pipelines.",
    "level": 0
  },
  {
    "anchor": [
      "body",
      0,
      0,
      0,
      179
    ],
    "breadcrumb": "6. Team and Experience",
    "style": "Heading 2",
    "text": "6. Team and Experience",
    "level": 2
  },
  {
    "anchor": [
      "body",
      0,
      0,
      0,
      180
    ],
    "breadcrumb": "Document Root",
    "style": "Normal",
    "text": "Section Structure:",
    "level": 0
  },
  {
    "anchor": [
      "body",
      0,
      0,
      0,
      181
    ],
    "breadcrumb": "Document Root",
    "style": "Normal",
    "text": "--\t• 6.1. Core Team Members",
    "level": 0
  },
  {
    "anchor": [
      "body",
      0,
      0,
      0,
      182
    ],
    "breadcrumb": "Document Root",
    "style": "Normal",
    "text": "--\t• 6.2. Relevant Experience",
    "level": 0
  },
  {
    "anchor": [
      "body",
      0,
      0,
      0,
      183
    ],
    "breadcrumb": "Document Root",
    "style": "Normal",
    "text": "--\t• 6.3. Similar Projects",
    "level": 0
  },
  {
    "anchor": [
      "body",
      0,
      0,
      0,
      184
    ],
    "breadcrumb": "Document Root",
    "style": "Normal",
    "text": "--\t• 6.4. Client References",
    "level": 0
  },
  {
    "anchor": [
      "body",
      0,
      0,
      0,
      186
    ],
    "breadcrumb": "Document Root",
    "style": "Normal",
    "text": "Technical Architecture",
    "level": 0
  },
  {
    "anchor": [
      "body",
      0,
      0,
      0,
      187
    ],
    "breadcrumb": "Document Root",
    "style": "Normal",
    "text": "We propose a cloud-native, microservices architecture built on modern containerization platforms with automated CI/CD pipelines.",
    "level": 0
  },
  {
    "anchor": [
      "body",
      0,
      0,
      0,
      189
    ],
    "breadcrumb": "7. Pricing",
    "style": "Heading 2",
    "text": "7. Pricing",
    "level": 2
  },
  {
    "anchor": [
      "body",
      0,
      0,
      0,
      190
    ],
    "breadcrumb": "Document Root",
    "style": "Normal",
    "text": "Section Structure:",
    "level": 0
  },
  {
    "anchor": [
      "body",
      0,
      0,
      0,
      191
    ],
    "breadcrumb": "Document Root",
    "style": "Normal",
    "text": "--\t• 7.1. Cost Breakdown",
    "level": 0
  },
  {
    "anchor": [
      "body",
      0,
      0,
      0,
      192
    ],
    "breadcrumb": "Document Root",
    "style": "Normal",
    "text": "--\t• 7.2. Pricing Model",
    "level": 0
  },
  {
    "anchor": [
      "body",
      0,
      0,
      0,
      193
    ],
    "breadcrumb": "Document Root",
    "style": "Normal",
    "text": "--\t• 7.3. Payment Terms",
    "level": 0
  },
  {
    "anchor": [
      "body",
      0,
      0,
      0,
      194
    ],
    "breadcrumb": "Document Root",
    "style": "Normal",
    "text": "--\t• 7.4. Value Analysis",
    "level": 0
  },
  {
    "anchor": [
      "body",
      0,
      0,
      0,
      196
    ],
    "breadcrumb": "Document Root",
    "style": "Normal",
    "text": "Financial Analysis",
    "level": 0
  },
  {
    "anchor": [
      "body",
      0,
      0,
      0,
      197
    ],
    "breadcrumb": "Document Root",
    "style": "Normal",
    "text": "Our comprehensive financial analysis demonstrates exceptional value proposition through strategic cost optimization and ROI maximization.",
    "level": 0
  },
  {
    "anchor": [
      "body",
      0,
      0,
      0,
      199
    ],
    "breadcrumb": "8. Terms and Conditions",
    "style": "Heading 2",
    "text": "8. Terms and Conditions",
    "level": 2
  },
  {
    "anchor": [
      "body",
      0,
      0,
      0,
      200
    ],
    "breadcrumb": "Document Root",
    "style": "Normal",
    "text": "Section Structure:",
    "level": 0
  },
  {
    "anchor": [
      "body",
      0,
      0,
      0,
      201
    ],
    "breadcrumb": "Document Root",
    "style": "Normal",
    "text": "--\t• 8.1. Contractual Terms",
    "level": 0
  },
  {
    "anchor": [
      "body",
      0,
      0,
      0,
      202
    ],
    "breadcrumb": "Document Root",
    "style": "Normal",
    "text": "--\t• 8.2. Service Level Agreements",
    "level": 0
  },
  {
    "anchor": [
      "body",
      0,
      0,
      0,
      203
    ],
    "breadcrumb": "Document Root",
    "style": "Normal",
    "text": "--\t• 8.3. Liability & Warranty",
    "level": 0
  },
  {
    "anchor": [
      "body",
      0,
      0,
      0,
      204
    ],
    "breadcrumb": "Document Root",
    "style": "Normal",
    "text": "--\t• 8.4. Intellectual Property",
    "level": 0
  },
  {
    "anchor": [
      "body",
      0,
      0,
      0,
      206
    ],
    "breadcrumb": "Document Root",
    "style": "Normal",
    "text": "Legal & Compliance",
    "level": 0
  },
  {
    "anchor": [
      "body",
      0,
      0,
      0,
      207
    ],
    "breadcrumb": "Document Root",
    "style": "Normal",
    "text": "Full adherence to all regulatory requirements including GDPR, HIPAA, and industry-specific compliance standards.",
    "level": 0
  },
  {
    "anchor": [
      "body",
      0,
      0,
      0,
      209
    ],
    "breadcrumb": "9. Additional Services",
    "style": "Heading 2",
    "text": "9. Additional Services",
    "level": 2
  },
  {
    "anchor": [
      "body",
      0,
      0,
      0,
      210
    ],
    "breadcrumb": "Document Root",
    "style": "Normal",
    "text": "Section Structure:",
    "level": 0
  },
  {
    "anchor": [
      "body",
      0,
      0,
      0,
      211
    ],
    "breadcrumb": "Document Root",
    "style": "Normal",
    "text": "--\t• 9.1. Optional Modules",
    "level": 0
  },
  {
    "anchor": [
      "body",
      0,
      0,
      0,
      212
    ],
    "breadcrumb": "Document Root",
    "style": "Normal",
    "text": "--\t• 9.2. Future Enhancements",
    "level": 0
  },
  {
    "anchor": [
      "body",
      0,
      0,
      0,
      213
    ],
    "breadcrumb": "Document Root",
    "style": "Normal",
    "text": "--\t• 9.3. Support Services",
    "level": 0
  },
  {
    "anchor": [
      "body",
      0,
      0,
      0,
      214
    ],
    "breadcrumb": "Document Root",
    "style": "Normal",
    "text": "--\t• 9.4. Training Programs",
    "level": 0
  },
  {
    "anchor": [
      "body",
      0,
      0,
      0,
      216
    ],
    "breadcrumb": "Document Root",
    "style": "Normal",
    "text": "Technical Architecture",
    "level": 0
  },
  {
    "anchor": [
      "body",
      0,
      0,
      0,
      217
    ],
    "breadcrumb": "Document Root",
    "style": "Normal",
    "text": "We propose a cloud-native, microservices architecture built on modern containerization platforms with automated CI/CD pipelines.",
    "level": 0
  },
  {
    "anchor": [
      "body",
      0,
      0,
      0,
      219
    ],
    "breadcrumb": "10. Appendices",
    "style": "Heading 2",
    "text": "10. Appendices",
    "level": 2
  },
  {
    "anchor": [
      "body",
      0,
      0,
      0,
      220
    ],
    "breadcrumb": "Document Root",
    "style": "Normal",
    "text": "Section Structure:",
    "level": 0
  },
  {
    "anchor": [
      "body",
      0,
      0,
      0,
      221
    ],
    "breadcrumb": "Document Root",
    "style": "Normal",
    "text": "--\t• 10.1. Technical Specifications",
    "level": 0
  },
  {
    "anchor": [
      "body",
      0,
      0,
      0,
      222
    ],
    "breadcrumb": "Document Root",
    "style": "Normal",
    "text": "--\t• 10.2. Certifications",
    "level": 0
  },
  {
    "anchor": [
      "body",
      0,
      0,
      0,
      223
    ],
    "breadcrumb": "Document Root",
    "style": "Normal",
    "text": "--\t• 10.3. Case Studies",
    "level": 0
  },
  {
    "anchor": [
      "body",
      0,
      0,
      0,
      224
    ],
    "breadcrumb": "Document Root",
    "style": "Normal",
    "text": "--\t• 10.4. Additional Documentation",
    "level": 0
  },
  {
    "anchor": [
      "body",
      0,
      0,
      0,
      226
    ],
    "breadcrumb": "10.1. Technical Specifications",
    "style": "Heading 3",
    "text": "10.1. Technical Specifications",
    "level": 3
  },
  {
    "anchor": [
      "body",
      0,
      0,
      0,
      227
    ],
    "breadcrumb": "Document Root",
    "style": "Normal",
    "text": "Detailed technical specifications, system requirements, and architecture diagrams are provided as supporting documentation.",
    "level": 0
  },
  {
    "anchor": [
      "body",
      0,
      0,
      0,
      228
    ],
    "breadcrumb": "10.2. Certifications",
    "style": "Heading 3",
    "text": "10.2. Certifications",
    "level": 3
  },
  {
    "anchor": [
      "body",
      0,
      0,
      0,
      229
    ],
    "breadcrumb": "Document Root",
    "style": "Normal",
    "text": "Complete documentation of our certifications, accreditations, and compliance attestations.",
    "level": 0
  },
  {
    "anchor": [
      "body",
      0,
      0,
      0,
      230
    ],
    "breadcrumb": "10.3. Case Studies",
    "style": "Heading 3",
    "text": "10.3. Case Studies",
    "level": 3
  },
  {
    "anchor": [
      "body",
      0,
      0,
      0,
      231
    ],
    "breadcrumb": "Document Root",
    "style": "Normal",
    "text": "Relevant case studies demonstrating successful implementations of similar solutions.",
    "level": 0
  },
  {
    "anchor": [
      "body",
      0,
      0,
      0,
      232
    ],
    "breadcrumb": "10.4. Additional Documentation",
    "style": "Heading 3",
    "text": "10.4. Additional Documentation",
    "level": 3
  },
  {
    "anchor": [
      "body",
      0,
      0,
      0,
      233
    ],
    "breadcrumb": "Document Root",
    "style": "Normal",
    "text": "Supporting materials including white papers, technical references, and methodology documentation.",
    "level": 0
  },
  {
    "anchor": [
      "body",
      0,
      0,
      0,
      235
    ],
    "breadcrumb": "Document Summary",
    "style": "Heading 2",
    "text": "Document Summary",
    "level": 2
  },
  {
    "anchor": [
      "body",
      0,
      0,
      0,
      236
    ],
    "breadcrumb": "Document Root",
    "style": "Normal",
    "text": "Generated: 2025-09-27T14:20:39.987003",
    "level": 0
  },
  {
    "anchor": [
      "body",
      0,
      0,
      0,
      237
    ],
    "breadcrumb": "Document Root",
    "style": "Normal",
    "text": "Total Sections: 10",
    "level": 0
  },
  {
    "anchor": [
      "body",
      0,
      0,
      0,
      238
    ],
    "breadcrumb": "Document Root",
    "style": "Normal",
    "text": "Teams Involved: finance_team, technical_team, legal_team, qa_team",
    "level": 0
  },
  {
    "anchor": [
      "body",
      0,
      0,
      0,
      239
    ],
    "breadcrumb": "Document Root",
    "style": "Normal",
    "text": "Processing Method: Multi-team structured generation",
    "level": 0
  },
  {
    "anchor": [
      "body",
      0,
      0,
      0,
      240
    ],
    "breadcrumb": "Document Root",
    "style": "Normal",
    "text": "This document was generated using an AI-powered proposal generation system.",
    "level": 0
  }
]